dataplate-lab/__init__.py
dataplate-lab/_version.py
dataplate-lab/handlers.py
dataplate_lab-0.3.1.data/data/etc/jupyter/jupyter_notebook_config.d/dataplate-lab.json
dataplate_lab-0.3.1.data/data/etc/jupyter/jupyter_server_config.d/dataplate-lab.json
setupbase/__init__.py
dataplate_lab-0.3.1.dist-info/LICENSE
dataplate_lab-0.3.1.dist-info/METADATA
dataplate_lab-0.3.1.dist-info/WHEEL
dataplate_lab-0.3.1.dist-info/top_level.txt
dataplate_lab-0.3.1.dist-info/RECORD
